AUTHORS.rst
CHANGES.rst
LICENSE
MANIFEST.in
README.rst
pushover.py
setup.py
test.py
python_pushover.egg-info/PKG-INFO
python_pushover.egg-info/SOURCES.txt
python_pushover.egg-info/dependency_links.txt
python_pushover.egg-info/entry_points.txt
python_pushover.egg-info/requires.txt
python_pushover.egg-info/top_level.txt