Metadata-Version: 1.0
Name: python-pushover
Version: 0.4
Summary: Comprehensive bindings and command line utility for the Pushover notification service
Home-page: https://github.com/Thibauth/python-pushover
Author: Thibaut Horel
Author-email: thibaut.horel+pushover@gmail.com
License: GNU GPLv3
Platform: UNKNOWN
